[
  {
    "context_label": "3 - Ermittlung des abziehbaren Verlustes und des vortragsfähigen Gewerbeverlustes (§ 10a Satz 9 in Verbindung mit § 8 Absatz 9 Satz 5 bis 8 )",
    "sections": [
      {
        "section_label": null,
        "rows": [
          {
            "row": null,
            "label": "Zeilen 78 bis 99: Bei Organgesellschaften im Falle der Anwachsung: Ohne übernommene Gewerbeverluste, die nach Abschluss des Gewinnabführungsvertrages bei der Personengesellschaft entstanden sind (R 10a.4 Satz 3 GewStR 2009; hierzu vergleiche Zeile 100)",
            "type": "note",
            "values": []
          }
        ],
        "sections": []
      },
      {
        "section_label": "Anfangsbestand",
        "rows": [
          {
            "row": "78",
            "label": "Festgestellter vortragsfähiger Gewerbeverlust zum Schluss des vorangegangenen Erhebungszeitraums für die Sparte (Zeile 98 des Vorjahres) (Euro)",
            "type": "text",
            "values": []
          },
          {
            "row": "79",
            "label": "Davon ab: Im Falle eines schädlichen Ereignisses im Sinne des § 10a Satz 11 GewStG in Verbindung mit § 8d Absatz 2 KStG: Untergang des festgestellten vortragsfähigen fortführungsgebundenen Gewerbeverlustes (Betrag laut Zeile 101) (Euro)",
            "type": "text",
            "values": []
          },
          {
            "row": "80",
            "label": "Dazu: Erhalt des vortragsfähigen fortführungsgebundenen Gewerbeverlustes nach § 10a Satz 11 GewStG in Verbindung mit § 8d Absatz 2 Satz 1 zweiter Halbsatz KStG durch entsprechende Anwendung des § 8c Absatz 1 Satz 5 bis 8 KStG bezogen auf die zum Schluss des vorangegangenen Erhebungszeitraums vorhandenen stillen Reserven (höchstens Betrag laut Zeile 79; laut gesonderter Ermittlung) (Euro)",
            "type": "text",
            "values": []
          },
          {
            "row": "81",
            "label": "Nur für Betriebe gewerblicher Art:Dazu: Übernommener vortragsfähiger Gewerbeverlust (§ 10a Satz 9 GewStG in Verbindung mit § 8 Absatz 8 KStG) (Zeile 132 des Vordrucks GewSt 1 A) (Euro)",
            "type": "text",
            "values": []
          },
          {
            "row": "82",
            "label": "Dazu: Übernommener Gewerbeverlust im Fall der Anwachsung oder der Verschmelzung einer Personengesellschaft auf einen Gesellschafter (R 10a.3 Absatz 3 Satz 9 Nummer 4 GewStR 2009, Zeile 130 des Vordrucks GewSt 1 A) (Euro)",
            "type": "text",
            "values": []
          },
          {
            "row": "83",
            "label": "Davon ab: Nach § 10a Satz 10 GewStG in Verbindung mit § 8c KStG (gegebenenfalls in Verbindung mit § 2 Absatz 4 Satz 1 und 2 UmwStG, § 20 Absatz 6 Satz 4 UmwStG) nicht abziehbarer Gewerbeverlust aus vorangegangenen Erhebungszeiträumen (Zeile 134 des Vordrucks GewSt 1 A) (Euro)",
            "type": "text",
            "values": []
          },
          {
            "row": "84",
            "label": "Davon ab: Bei der übertragenden Körperschaft im Fall der Abspaltung wegfallender Gewerbeverlust aus vorangegangenen Erhebungszeiträumen (§ 18 Absatz 1 in Verbindung mit § 16 und § 15 Absatz 3 beziehungsweise § 19 Absatz 2 in Verbindung mit § 15 Absatz 3 UmwStG) (Zeile 133 des Vordrucks GewSt 1 A) (Euro)",
            "type": "text",
            "values": []
          },
          {
            "row": "85",
            "label": "Davon ab: Minderung des vortragsfähigen Gewerbeverlustes nach § 7b Absatz 2 Satz 1 Nummer 2 oder 3 erster Halbsatz gegebenenfalls in Verbindung mit Satz 2 beziehungsweise Absatz 3 GewStG (Euro)",
            "type": "text",
            "values": []
          }
        ],
        "sections": []
      },
      {
        "section_label": "Negativer Gewerbeertrag",
        "rows": [
          {
            "row": null,
            "label": "Nicht bei Organgesellschaften",
            "type": "note",
            "values": []
          },
          {
            "row": "86",
            "label": "Dazu: Berücksichtigungsfähiger Gewerbeverlust des laufenden Erhebungszeitraums(Negativer Betrag laut Zeile 67 beziehungsweise, wenn Betrag laut Zeile 66 Vorspalte negativ: Betrag laut Zeile 66 Vorspalte (Betrag ohne Vorzeichen eintragen)) (Euro)",
            "type": "text",
            "values": []
          },
          {
            "row": "87",
            "label": "Zwischensumme (Euro)",
            "type": "text",
            "values": []
          }
        ],
        "sections": []
      },
      {
        "section_label": "Verrechnung des positiven Gewerbeertrages mit dem Verlustvortrag",
        "rows": [
          {
            "row": null,
            "label": "Zeilen 88 bis 96: Nicht bei Organgesellschaften",
            "type": "note",
            "values": []
          },
          {
            "row": "88",
            "label": "Positiver Gewerbeertrag der Sparte vor Verlustabzug (positiver Betrag laut Zeile 68)",
            "type": "text",
            "values": [
              "Vorspalte (Euro)"
            ]
          },
          {
            "row": "89",
            "label": "Im Falle von Umwandlungen mit steuerlicher Rückwirkung beim übernehmenden Rechtsträger:Davon ab: Im Betrag laut Zeile 88 enthaltener positiver Gewerbeertrag des übertragenden oder einbringenden Rechtsträgers im Rückwirkungszeitraum (vergleiche § 2 Absatz 4 Satz 3 und 4 UmwStG) - Summe der Beträge laut Zeilen 64 und 65 (Zeilen 120 und 121 des Vordrucks GewSt 1 A)",
            "type": "text",
            "values": [
              "Vorspalte (Euro)"
            ]
          },
          {
            "row": "90",
            "label": "Zwischensumme",
            "type": "text",
            "values": [
              "Vorspalte (Euro)"
            ]
          },
          {
            "row": "91",
            "label": "Davon ab: Niedrigerer Betrag aus Zeile 87 oder 90 (höchstens 1 Million €)",
            "type": "text",
            "values": [
              "Vorspalte (Euro)"
            ]
          },
          {
            "row": "92",
            "label": "Zwischensumme",
            "type": "text",
            "values": [
              "Vorspalte (Euro)"
            ]
          },
          {
            "row": "93",
            "label": "Nach § 10a Satz 2 GewStG zu berücksichtigender Verlustabzug:Betrag laut Zeile 87 abzüglich Betrag laut Zeile 91, höchstens 60 % des Betrages aus Zeile 92",
            "type": "text",
            "values": [
              "Vorspalte (Euro)"
            ]
          },
          {
            "row": "94",
            "label": "Zwischensumme zur Ermittlung des zu berücksichtigenden Verlustvortrags (Summe der Beträge laut Zeilen 91 und 93 Vorspalte)",
            "type": "text",
            "values": [
              "Vorspalte (Euro)"
            ]
          },
          {
            "row": "95",
            "label": "Davon ab: Betrag laut Zeile 85 (§ 7b Absatz 2 Satz 1 Nummer 3 zweiter Halbsatz GewStG), höchstens Betrag laut Zeile 94",
            "type": "text",
            "values": [
              "Vorspalte (Euro)"
            ]
          },
          {
            "row": "96",
            "label": "Betrag des zu berücksichtigenden Verlustvortrags (Übertrag in die Hauptspalte mit umgekehrtem Vorzeichen)",
            "type": "text",
            "values": [
              "Vorspalte (Euro)",
              "Hauptspalte (Euro)"
            ]
          },
          {
            "row": "97",
            "label": "Davon ab: Aufgrund der Veräußerung oder Aufgabe eines angewachsenen Teilbetriebes wegfallender vortragsfähiger Gewerbeverlust (Zeile 141 des Vordrucks GewSt 1 A)",
            "type": "text",
            "values": [
              "Hauptspalte (Euro)"
            ]
          }
        ],
        "sections": []
      },
      {
        "section_label": "Endbestand",
        "rows": [
          {
            "row": "98",
            "label": "Vortragsfähiger Gewerbeverlust für die Sparte zum Schluss des Erhebungszeitraums (Euro)",
            "type": "text",
            "values": []
          },
          {
            "row": "99",
            "label": "Nicht bei Organgesellschaften:Insgesamt vorzunehmender Verlustabzug (Betrag laut Zeile 96 Vorspalte; Übertrag nach Zeile 69) (Euro)",
            "type": "text",
            "values": []
          },
          {
            "row": "100",
            "label": "Nur bei Organgesellschaften im Falle der Anwachsung:Vortragsfähiger Gewerbeverlust, der nach dem rechtswirksamen Abschluss des Gewinnabführungsvertrages bei der Personengesellschaft entstanden ist (R 10a.4 Satz 3 GewStR 2009), für die Tätigkeit zum Schluss des Erhebungszeitraums (laut gesonderter Ermittlung analog zu den Zeilen 78 bis 99) (Euro)",
            "type": "text",
            "values": []
          }
        ],
        "sections": []
      }
    ]
  }
]