[
  {
    "context_label": "7 - Hinzurechnungen",
    "sections": [
      {
        "section_label": "Finanzierungsanteile nach § 8 Nummer 1 GewStG des (ersten) Wirtschaftsjahres (ohne Kürzung um die Beträge laut Zeilen 79 und 80)",
        "rows": [
          {
            "row": null,
            "label": "(enden im Erhebungszeitraum zwei Wirtschaftsjahre, sind zusätzlich die Zeilen 58 bis 65 auszufüllen)",
            "type": "note",
            "values": []
          },
          {
            "row": null,
            "label": "Beträge in voller Höhe eintragen, gegebenenfalls laut gesonderter Einzelaufstellung; der Hinzurechnungsbetrag wird von Amts wegen ermittelt.",
            "type": "note",
            "values": []
          },
          {
            "row": "50",
            "label": "Entgelte für Schulden (§ 8 Nummer 1 Buchstabe a GewStG) (Euro)",
            "type": "text",
            "values": []
          },
          {
            "row": "51",
            "label": "Renten und dauernde Lasten (§ 8 Nummer 1 Buchstabe b GewStG) (Euro)",
            "type": "text",
            "values": []
          },
          {
            "row": "52",
            "label": "Gewinnanteile der stillen Gesellschafter (§ 8 Nummer 1 Buchstabe c GewStG) (Euro)",
            "type": "text",
            "values": []
          },
          {
            "row": "53",
            "label": "Miet- und Pachtzinsen (einschließlich Leasingraten) für die Benutzung fremder beweglicher Betriebsanlagegüter (§ 8 Nummer 1 Buchstabe d Satz 1 GewStG) (ohne Beträge laut Zeile 54) (Euro)",
            "type": "text",
            "values": []
          },
          {
            "row": "54",
            "label": "Miet- und Pachtzinsen (einschließlich Leasingraten) für Elektrofahrzeuge, begünstigte Hybridelektrofahrzeuge und Fahrräder im Sinne des § 8 Nummer 1 Buchstabe d Satz 2 GewStG aus Verträgen, die nach dem 31.12.2019 abgeschlossen worden sind (Euro)",
            "type": "text",
            "values": []
          },
          {
            "row": "55",
            "label": "Miet- und Pachtzinsen (einschließlich Leasingraten) für die Benutzung fremder unbeweglicher Betriebsanlagegüter (§ 8 Nummer 1 Buchstabe e GewStG) (Euro)",
            "type": "text",
            "values": []
          },
          {
            "row": "56",
            "label": "Aufwendungen für die zeitlich befristete Überlassung von Rechten - insbesondere Konzessionen und Lizenzen - (§ 8 Nummer 1 Buchstabe f GewStG) (Euro)",
            "type": "text",
            "values": []
          },
          {
            "row": "57",
            "label": "Im Betrag laut Zeile 56 enthaltene Vergütungen im Sinne des § 50a Absatz 1 Nummer 3 EStG an beschränkt steuerpflichtige Zahlungsempfänger (Euro)",
            "type": "text",
            "values": []
          }
        ],
        "sections": []
      },
      {
        "section_label": "Finanzierungsanteile nach § 8 Nummer 1 GewStG für ein zweites, im Erhebungszeitraum endendes Wirtschaftsjahr (ohne Kürzung um die Beträge laut Zeilen 79 und 80)",
        "rows": [
          {
            "row": null,
            "label": "Beträge in voller Höhe eintragen, gegebenenfalls laut gesonderter Einzelaufstellung; der Hinzurechnungsbetrag wird von Amts wegen ermittelt.",
            "type": "note",
            "values": []
          },
          {
            "row": "58",
            "label": "Entgelte für Schulden (§ 8 Nummer 1 Buchstabe a GewStG) (Euro)",
            "type": "text",
            "values": []
          },
          {
            "row": "59",
            "label": "Renten und dauernde Lasten (§ 8 Nummer 1 Buchstabe b GewStG) (Euro)",
            "type": "text",
            "values": []
          },
          {
            "row": "60",
            "label": "Gewinnanteile der stillen Gesellschafter (§ 8 Nummer 1 Buchstabe c GewStG) (Euro)",
            "type": "text",
            "values": []
          },
          {
            "row": "61",
            "label": "Miet- und Pachtzinsen (einschließlich Leasingraten) für die Benutzung fremder beweglicher Betriebsanlagegüter (§ 8 Nummer 1 Buchstabe d Satz 1 GewStG) (ohne Beträge laut Zeile 62) (Euro)",
            "type": "text",
            "values": []
          },
          {
            "row": "62",
            "label": "Miet- und Pachtzinsen (einschließlich Leasingraten) für Elektrofahrzeuge, begünstigte Hybridelektrofahrzeuge und Fahrräder im Sinne des § 8 Nummer 1 Buchstabe d Satz 2 GewStG aus Verträgen, die nach dem 31.12.2019 abgeschlossen worden sind (Euro)",
            "type": "text",
            "values": []
          },
          {
            "row": "63",
            "label": "Miet- und Pachtzinsen (einschließlich Leasingraten) für die Benutzung fremder unbeweglicher Betriebsanlagegüter (§ 8 Nummer 1 Buchstabe e GewStG) (Euro)",
            "type": "text",
            "values": []
          },
          {
            "row": "64",
            "label": "Aufwendungen für die zeitlich befristete Überlassung von Rechten - insbesondere Konzessionen und Lizenzen - (§ 8 Nummer 1 Buchstabe f GewStG) (Euro)",
            "type": "text",
            "values": []
          },
          {
            "row": "65",
            "label": "Im Betrag laut Zeile 64 enthaltene Vergütungen im Sinne des § 50a Absatz 1 Nummer 3 EStG an beschränkt steuerpflichtige Zahlungsempfänger (Euro)",
            "type": "text",
            "values": []
          }
        ],
        "sections": []
      },
      {
        "section_label": "Hinzurechnung nach § 8 Nummer 4 GewStG",
        "rows": [
          {
            "row": "66",
            "label": "Nur bei einer Kommanditgesellschaft auf Aktien:Gewinnanteile der in § 8 Nummer 4 GewStG bezeichneten Art an persönlich haftende Gesellschafter (Euro)",
            "type": "text",
            "values": []
          }
        ],
        "sections": []
      },
      {
        "section_label": "Anteile am Verlust von in- und/oder ausländischen Personengesellschaften (§ 8 Nummer 8 GewStG)",
        "rows": [
          {
            "row": null,
            "label": "laut gesonderter Einzelaufstellung",
            "type": "note",
            "values": []
          }
        ],
        "sections": [
          {
            "section_label": null,
            "rows": [
              {
                "row": "67c",
                "label": "Summe der Anteile am Verlust von in- und/oder ausländischen Personengesellschaften (§ 8 Nummer 8 GewStG; Betrag ohne Minuszeichen eintragen) (Euro)",
                "type": "text",
                "values": []
              }
            ],
            "sections": [
              {
                "section_label": "Name der Personengesellschaft",
                "rows": [
                  {
                    "row": null,
                    "label": "Name der Personengesellschaft",
                    "type": "repeater",
                    "values": []
                  }
                ],
                "sections": []
              }
            ]
          }
        ]
      },
      {
        "section_label": "Hinzurechnung nach § 8 Nummer 10 bis 12 GewStG",
        "rows": [
          {
            "row": "68",
            "label": "Ausschüttungs- und abführungsbedingte Gewinnminderungen bei Beteiligungsbesitz (§ 8 Nummer 10 GewStG); auch soweit die Gewinnminderung Folge einer Auskehrung von Liquidationsraten ist (Euro)",
            "type": "text",
            "values": []
          },
          {
            "row": "69",
            "label": "Ausländische Steuern, soweit sie auf Gewinne oder Gewinnanteile entfallen, die nach § 9 GewStG gekürzt werden oder sonst nicht im Gewerbeertrag enthalten sind (§ 8 Nummer 12 GewStG) (Euro)",
            "type": "text",
            "values": []
          }
        ],
        "sections": []
      }
    ]
  }
]